[{
  "_id": 1,
  "templateId": "whiteboard",
  "projectName": "test",
  "thumbnail": "https://getidea-s3.s3.ap-northeast-2.amazonaws.com/thumbnailImage/whiteboard.png",
  "lastUpdateTime": {
    "$date": "2024-02-15T10:47:14.573Z"
  },
  "data": {
    "Rect1": {},
    "Circle2": {
      "id": "Circle2",
      "type": "Circle",
      "stroke": "",
      "x": -92.8667320151747,
      "y": -99.08362578348564,
      "radius": 50,
      "fill": "#000000",
      "ty": "Shape",
      "draggable": true,
      "rotation": 0,
      "scaleX": 1,
      "scaleY": 1,
      "offsetX": 0,
      "offsetY": 0,
      "skewX": 0,
      "skewY": 0
    },
    "Arrow12": {
      "id": "Arrow12",
      "points": [
        null,
        null,
        null,
        null
      ],
      "pointerLength": 20,
      "stroke": "#000000",
      "rotation": 0,
      "strokeWidth": 10,
      "fill": "#000000",
      "ty": "Line",
      "type": "Arrow",
      "lineJoin": "round",
      "x": 387.35485874353395,
      "y": -73.66874118262271,
      "draggable": true,
      "dashEnabled": true,
      "scaleX": 1,
      "scaleY": 1,
      "offsetX": 0,
      "offsetY": 0,
      "skewX": 0,
      "skewY": 0
    },
    "Arrow11": {
      "id": "Arrow11",
      "points": [
        null,
        null,
        null,
        null
      ],
      "pointerLength": 20,
      "stroke": "#000000",
      "rotation": 0,
      "strokeWidth": 10,
      "fill": "#000000",
      "ty": "Line",
      "type": "Arrow",
      "lineJoin": "round",
      "x": 206.8727311783722,
      "y": -73.581005663043,
      "draggable": true,
      "dashEnabled": true,
      "scaleX": 1,
      "scaleY": 1,
      "offsetX": 0,
      "offsetY": 0,
      "skewX": 0,
      "skewY": 0
    },
    "Text-2": {
      "id": "Text-2",
      "text": "asdfasdf",
      "x": 691.6353818996739,
      "y": 54.72319558779901,
      "ty": "Text",
      "draggable": true,
      "style": {
        "zIndex": 100
      },
      "fill": "black",
      "rotation": 0,
      "scaleX": 1,
      "scaleY": 1,
      "offsetX": 0,
      "offsetY": 0,
      "skewX": 0,
      "skewY": 0
    },
    "Text-3": {
      "id": "Text-3",
      "text": "asdfasdfsdf",
      "x": 946.7708225394244,
      "y": 114.41125999780303,
      "ty": "Text",
      "draggable": true,
      "style": {
        "zIndex": 100
      },
      "fill": "black",
      "rotation": 0,
      "scaleX": 1,
      "scaleY": 1,
      "offsetX": 0,
      "offsetY": 0,
      "skewX": 0,
      "skewY": 0
    },
    "Text-4": {},
    "Rect217af859-4fef-486e-bb87-ce23beea7fe9": {
      "id": "Rect217af859-4fef-486e-bb87-ce23beea7fe9",
      "type": "Rect",
      "stroke": "",
      "strokeWidth": 3,
      "x": 647.0707331862653,
      "y": -70.94213530423161,
      "width": 100,
      "height": 100,
      "fill": "#000000",
      "ty": "Rect",
      "draggable": true,
      "rotation": 0,
      "scaleX": 1,
      "scaleY": 1,
      "offsetX": 0,
      "offsetY": 0,
      "skewX": 0,
      "skewY": 0
    },
    "Circlefbd7a2cd-fe7c-4893-abbe-42fce17adb81": {
      "id": "Circlefbd7a2cd-fe7c-4893-abbe-42fce17adb81",
      "type": "Circle",
      "stroke": "",
      "strokeWidth": 3,
      "x": 751.214780269226,
      "y": 249.9043558747628,
      "radius": 50,
      "fill": "#000000",
      "ty": "Circle",
      "draggable": true,
      "rotation": 0,
      "scaleX": 1,
      "scaleY": 1,
      "offsetX": 0,
      "offsetY": 0,
      "skewX": 0,
      "skewY": 0
    },
    "RegularPolygon3": {
      "id": "RegularPolygon3",
      "type": "RegularPolygon",
      "stroke": "",
      "x": 533.1479869758004,
      "y": 297.88140128470593,
      "sides": 3,
      "radius": 50,
      "fill": "#000000",
      "ty": "Shape",
      "draggable": true,
      "rotation": 0,
      "scaleX": 1,
      "scaleY": 1,
      "offsetX": 0,
      "offsetY": 0,
      "skewX": 0,
      "skewY": 0
    },
    "Rect3": {
      "id": "Rect3",
      "type": "Rect",
      "stroke": "",
      "x": 960.2788160413631,
      "y": 327.86705466592036,
      "width": 100,
      "height": 100,
      "fill": "#000000",
      "ty": "Shape",
      "draggable": true,
      "rotation": 0,
      "scaleX": 1,
      "scaleY": 1,
      "offsetX": 0,
      "offsetY": 0,
      "skewX": 0,
      "skewY": 0
    },
    "Circle3": {
      "id": "Circle3",
      "type": "Circle",
      "stroke": "",
      "x": 555,
      "y": 362.9818876222441,
      "radius": 50,
      "fill": "#000000",
      "ty": "Shape",
      "draggable": true,
      "rotation": 0,
      "scaleX": 1,
      "scaleY": 1,
      "offsetX": 0,
      "offsetY": 0,
      "skewX": 0,
      "skewY": 0
    },
    "RegularPolygon4": {
      "id": "RegularPolygon4",
      "type": "RegularPolygon",
      "stroke": "",
      "x": 446,
      "y": 250.98836872866153,
      "sides": 3,
      "radius": 50,
      "fill": "#000000",
      "ty": "Shape",
      "draggable": true,
      "rotation": 0,
      "scaleX": 1,
      "scaleY": 1,
      "offsetX": 0,
      "offsetY": 0,
      "skewX": 0,
      "skewY": 0
    }
  }
},
{
  "_id": 2,
  "templateId": "whiteboard",
  "projectName": "fTest2",
  "thumbnail": "https://getidea-s3.s3.ap-northeast-2.amazonaws.com/thumbnailImage/whiteboard.png",
  "lastUpdateTime": {
    "$date": "2024-02-15T12:38:42.438Z"
  },
  "data": {
    "Rect20405624-4252-40ae-8c0f-4aca7ca86a5b": {
      "id": "Rect20405624-4252-40ae-8c0f-4aca7ca86a5b",
      "type": "Rect",
      "stroke": "",
      "x": 368.0974324188502,
      "y": 118.96700277679312,
      "width": 100,
      "height": 100,
      "fill": "#000000",
      "ty": "Rect",
      "draggable": true,
      "rotation": 0,
      "scaleX": 1,
      "scaleY": 1,
      "offsetX": 0,
      "offsetY": 0,
      "skewX": 0,
      "skewY": 0
    },
    "Rectba096024-4f4f-42d6-8fe2-0c4f44e23b76": {
      "id": "Rectba096024-4f4f-42d6-8fe2-0c4f44e23b76",
      "type": "Rect",
      "stroke": "",
      "x": 878.4601266147205,
      "y": 461.9534596924587,
      "width": 100,
      "height": 100,
      "fill": "#000000",
      "ty": "Rect",
      "draggable": true,
      "rotation": 0,
      "scaleX": 1,
      "scaleY": 1,
      "offsetX": 0,
      "offsetY": 0,
      "skewX": 0,
      "skewY": 0
    },
    "Circle953fa11b-c1e6-4991-ad72-2cbcc1c71291": {
      "id": "Circle953fa11b-c1e6-4991-ad72-2cbcc1c71291",
      "type": "Circle",
      "stroke": "",
      "x": -204.85808336649035,
      "y": 358.78944319093864,
      "radius": 50,
      "fill": "#000000",
      "ty": "Circle",
      "draggable": true,
      "rotation": 0,
      "scaleX": 1,
      "scaleY": 1,
      "offsetX": 0,
      "offsetY": 0,
      "skewX": 0,
      "skewY": 0
    },
    "RegularPolygon062c6fcb-8505-4c1c-b67b-0e6cd35ee2fe": {
      "id": "RegularPolygon062c6fcb-8505-4c1c-b67b-0e6cd35ee2fe",
      "type": "RegularPolygon",
      "stroke": "",
      "x": 922.249585268259,
      "y": 173.88563432015022,
      "sides": 3,
      "radius": 50,
      "fill": "#000000",
      "ty": "RegularPolygon",
      "draggable": true,
      "rotation": 0,
      "scaleX": 1,
      "scaleY": 1,
      "offsetX": 0,
      "offsetY": 0,
      "skewX": 0,
      "skewY": 0
    },
    "Circlefb38754c-2124-4947-bb0c-236ab8faa3b6": {
      "id": "Circlefb38754c-2124-4947-bb0c-236ab8faa3b6",
      "type": "Circle",
      "stroke": "",
      "x": -297.6679794541428,
      "y": 65.55501247373934,
      "radius": 50,
      "fill": "#000000",
      "ty": "Circle",
      "draggable": true,
      "rotation": 0,
      "scaleX": 1,
      "scaleY": 1,
      "offsetX": 0,
      "offsetY": 0,
      "skewX": 0,
      "skewY": 0
    },
    "RegularPolygon7a5d5076-1976-4ccc-8717-8c934bfd1652": {
      "id": "RegularPolygon7a5d5076-1976-4ccc-8717-8c934bfd1652",
      "type": "RegularPolygon",
      "stroke": "",
      "x": -2258.1376510917453,
      "y": 1405.0727600304008,
      "sides": 3,
      "radius": 633.6135169970611,
      "fill": "#000000",
      "ty": "RegularPolygon",
      "draggable": true,
      "rotation": 0,
      "scaleX": 1,
      "scaleY": 1,
      "offsetX": 0,
      "offsetY": 0,
      "skewX": 0,
      "skewY": 0,
      "width": 1267.2270339941194,
      "height": 1267.2270339941222
    },
    "Circlec3ce9483-180f-447a-aa58-95799102415e": {
      "id": "Circlec3ce9483-180f-447a-aa58-95799102415e",
      "type": "Circle",
      "stroke": "",
      "x": 551.1535020183767,
      "y": 333.8641853421632,
      "radius": 50,
      "fill": "#dd7e7e",
      "ty": "Circle",
      "draggable": true,
      "rotation": 0,
      "scaleX": 1,
      "scaleY": 1,
      "offsetX": 0,
      "offsetY": 0,
      "skewX": 0,
      "skewY": 0
    },
    "image20b0232f-d4b1-42e3-ae8d-948d962582da": {
      "id": "image20b0232f-d4b1-42e3-ae8d-948d962582da",
      "src": "/img/template2_6hats/hat2_red.svg",
      "x": -402.45805468767594,
      "y": -18.94086999360286,
      "ty": "Image",
      "type": "Image",
      "image": {},
      "width": 200,
      "height": 170.04048582995952,
      "draggable": true,
      "rotation": 0,
      "scaleX": 1,
      "scaleY": 1,
      "offsetX": 0,
      "offsetY": 0,
      "skewX": 0,
      "skewY": 0
    },
    "image0a83728b-895b-46e0-839b-c76d51635071": {
      "id": "image0a83728b-895b-46e0-839b-c76d51635071",
      "src": "/img/template2_6hats/hat3_yellow.svg",
      "x": 144.89853677115863,
      "y": 418.9447250850183,
      "ty": "Image",
      "type": "Image",
      "image": {},
      "width": 200,
      "height": 170.04048582995952,
      "draggable": true,
      "rotation": 0,
      "scaleX": 1,
      "scaleY": 1,
      "offsetX": 0,
      "offsetY": 0,
      "skewX": 0,
      "skewY": 0
    },
    "image80449547-4d74-46f0-8ce5-b6ed149f65f9": {
      "id": "image80449547-4d74-46f0-8ce5-b6ed149f65f9",
      "src": "/img/template2_6hats/hat3_yellow.svg",
      "x": -38.155225553401124,
      "y": -249.31614911589477,
      "ty": "Image",
      "type": "Image",
      "image": {},
      "width": 200,
      "height": 170.04048582995952,
      "draggable": true,
      "rotation": 0,
      "scaleX": 1,
      "scaleY": 1,
      "offsetX": 0,
      "offsetY": 0,
      "skewX": 0,
      "skewY": 0
    },
    "Recta1fe8742-12e2-45e4-881b-2e84480a4d47": {
      "id": "Recta1fe8742-12e2-45e4-881b-2e84480a4d47",
      "type": "Rect",
      "stroke": "",
      "strokeWidth": 3,
      "x": 567.1584042784449,
      "y": 167.9435699661101,
      "width": 100,
      "height": 100,
      "fill": "#000000",
      "ty": "Rect",
      "draggable": true,
      "rotation": 0,
      "scaleX": 1,
      "scaleY": 1,
      "offsetX": 0,
      "offsetY": 0,
      "skewX": 0,
      "skewY": 0
    },
    "Rect3af9b589-24cd-47a9-8aa0-95a8418dcfaa": {
      "id": "Rect3af9b589-24cd-47a9-8aa0-95a8418dcfaa",
      "type": "Rect",
      "stroke": "",
      "strokeWidth": 3,
      "x": 469.12837793552876,
      "y": 102.97465430681216,
      "width": 100,
      "height": 100,
      "fill": "#000000",
      "ty": "Rect",
      "draggable": true,
      "rotation": 0,
      "scaleX": 1,
      "scaleY": 1,
      "offsetX": 0,
      "offsetY": 0,
      "skewX": 0,
      "skewY": 0
    },
    "Rect3f59caa3-e153-414d-9fe6-68f46aadde98": {
      "id": "Rect3f59caa3-e153-414d-9fe6-68f46aadde98",
      "type": "Rect",
      "stroke": "",
      "strokeWidth": 3,
      "x": 314.0808872911207,
      "y": 257.90053010975333,
      "width": 100,
      "height": 100,
      "fill": "#000000",
      "ty": "Rect",
      "draggable": true,
      "rotation": 0,
      "scaleX": 1,
      "scaleY": 1,
      "offsetX": 0,
      "offsetY": 0,
      "skewX": 0,
      "skewY": 0
    },
    "Circlea76f1a6a-7315-497d-af1a-047c0e8605e9": {
      "id": "Circlea76f1a6a-7315-497d-af1a-047c0e8605e9",
      "type": "Circle",
      "stroke": "#c41717",
      "strokeWidth": "3",
      "x": 349.0916109850194,
      "y": 179.93783131859584,
      "radius": 50,
      "fill": "#000000",
      "ty": "Circle",
      "draggable": true,
      "rotation": 0,
      "scaleX": 1,
      "scaleY": 1,
      "offsetX": 0,
      "offsetY": 0,
      "skewX": 0,
      "skewY": 0
    },
    "RegularPolygonbd9d2d8e-5ba7-40cc-9270-7ee5915c81b9": {
      "id": "RegularPolygonbd9d2d8e-5ba7-40cc-9270-7ee5915c81b9",
      "type": "RegularPolygon",
      "stroke": "",
      "strokeWidth": 3,
      "x": 444.4121123295792,
      "y": 307.8729714448033,
      "sides": 3,
      "radius": 63.1491873571265,
      "fill": "#000000",
      "ty": "RegularPolygon",
      "draggable": true,
      "rotation": 88.92362633634421,
      "scaleX": 1,
      "scaleY": 1,
      "offsetX": 0,
      "offsetY": 0,
      "skewX": 5.785572823775357e-16,
      "skewY": 0,
      "width": 126.29837471425296,
      "height": 126.298374714253
    },
    "Circle69a2a3dc-6f97-4a88-ac14-f46547103dff": {
      "id": "Circle69a2a3dc-6f97-4a88-ac14-f46547103dff",
      "type": "Circle",
      "stroke": "#e8a6a6",
      "strokeWidth": "10",
      "x": 254.55598724640663,
      "y": 308.32773305984637,
      "radius": 49.999995143106645,
      "fill": "#000000",
      "ty": "Circle",
      "draggable": true,
      "rotation": 0,
      "scaleX": 1,
      "scaleY": 1,
      "offsetX": 0,
      "offsetY": 0,
      "skewX": 0,
      "skewY": 0,
      "width": 99.99999028621328,
      "height": 99.99999028621329
    },
    "Rect7d6eec2a-beb8-4f46-aeb6-8d7a823af744": {
      "id": "Rect7d6eec2a-beb8-4f46-aeb6-8d7a823af744",
      "type": "Rect",
      "stroke": "",
      "strokeWidth": 3,
      "x": 214.14798697580056,
      "y": 503.900586845,
      "width": 100,
      "height": 100,
      "fill": "#000000",
      "ty": "Rect",
      "draggable": true,
      "rotation": 0,
      "scaleX": 1,
      "scaleY": 1,
      "offsetX": 0,
      "offsetY": 0,
      "skewX": 0,
      "skewY": 0
    },
    "Circle3bc6486d-a26f-4c0c-81c6-19e8feee3bef": {
      "id": "Circle3bc6486d-a26f-4c0c-81c6-19e8feee3bef",
      "type": "Circle",
      "stroke": "#704343",
      "strokeWidth": "3",
      "x": 259.06403577213723,
      "y": 200.92778868544593,
      "radius": 50,
      "fill": "#c87e7e",
      "ty": "Circle",
      "draggable": true,
      "rotation": 0,
      "scaleX": 1,
      "scaleY": 1,
      "offsetX": 0,
      "offsetY": 0,
      "skewX": 0,
      "skewY": 0
    },
    "Rect719eceeb-b75e-43c5-954f-18d4704de445": {
      "id": "Rect719eceeb-b75e-43c5-954f-18d4704de445",
      "type": "Rect",
      "stroke": "#b15d5d",
      "strokeWidth": "10",
      "x": 273.06832524969667,
      "y": 261.89861722724856,
      "width": 100,
      "height": 100,
      "fill": "#000000",
      "ty": "Rect",
      "draggable": true,
      "rotation": 0,
      "scaleX": 1,
      "scaleY": 1,
      "offsetX": 0,
      "offsetY": 0,
      "skewX": 0,
      "skewY": 0
    },
    "Rectc5747898-cf10-4274-b66b-9b43c076461f": {
      "id": "Rectc5747898-cf10-4274-b66b-9b43c076461f",
      "type": "Rect",
      "stroke": "#c43636",
      "strokeWidth": "5",
      "x": 509.04060294657324,
      "y": 425.2204759769299,
      "width": 100,
      "height": 100,
      "fill": "#000000",
      "ty": "Rect",
      "draggable": true,
      "rotation": 0,
      "scaleX": 1,
      "scaleY": 1,
      "offsetX": 0,
      "offsetY": 0,
      "skewX": 0,
      "skewY": 0
    },
    "Rect5791a2ec-6a09-454f-bef4-7e41abce9b5d": {
      "id": "Rect5791a2ec-6a09-454f-bef4-7e41abce9b5d",
      "type": "Rect",
      "stroke": "#b06969",
      "strokeWidth": 3,
      "x": 667.1481135251535,
      "y": 278.9051998527645,
      "width": 100,
      "height": 100,
      "fill": "#000000",
      "ty": "Rect",
      "draggable": true,
      "rotation": 0,
      "scaleX": 1,
      "scaleY": 1,
      "offsetX": 0,
      "offsetY": 0,
      "skewX": 0,
      "skewY": 0
    },
    "Rectd740a7ca-5e40-43d1-acbd-3d7f2d974fed": {
      "id": "Rectd740a7ca-5e40-43d1-acbd-3d7f2d974fed",
      "type": "Rect",
      "stroke": "",
      "strokeWidth": 3,
      "x": 449.07068904564414,
      "y": 406.98438571654964,
      "width": 284.5079469433305,
      "height": 284.50794694333047,
      "fill": "#000000",
      "ty": "Rect",
      "draggable": true,
      "rotation": 0,
      "scaleX": 1,
      "scaleY": 1,
      "offsetX": 0,
      "offsetY": 0,
      "skewX": 0,
      "skewY": 0
    },
    "Circlec2a78431-c9da-413e-b781-ee5c720a70b4": {
      "id": "Circlec2a78431-c9da-413e-b781-ee5c720a70b4",
      "type": "Circle",
      "stroke": "#a22a2a",
      "strokeWidth": 3,
      "x": 232.76598074606324,
      "y": 189.08345559986628,
      "radius": 50,
      "fill": "#b34747",
      "ty": "Circle",
      "draggable": true,
      "rotation": 0,
      "scaleX": 1,
      "scaleY": 1,
      "offsetX": 0,
      "offsetY": 0,
      "skewX": 0,
      "skewY": 0
    },
    "Rect751de96f-4431-42c7-95f3-3a896f8f9d2a": {
      "id": "Rect751de96f-4431-42c7-95f3-3a896f8f9d2a",
      "type": "Rect",
      "stroke": "",
      "x": 2676.4375898743724,
      "y": 672.7885647152997,
      "width": 100,
      "height": 100,
      "fill": "#000000",
      "ty": "Rect",
      "draggable": true,
      "rotation": 0,
      "scaleX": 1,
      "scaleY": 1,
      "offsetX": 0,
      "offsetY": 0,
      "skewX": 0,
      "skewY": 0
    },
    "Rect5b7f68bc-5052-4d62-b6f5-df15c33cc880": {
      "id": "Rect5b7f68bc-5052-4d62-b6f5-df15c33cc880",
      "type": "Rect",
      "stroke": "",
      "x": 1927.3551983091686,
      "y": 799.7256762134502,
      "width": 100,
      "height": 100,
      "fill": "#000000",
      "ty": "Rect",
      "draggable": true,
      "rotation": 0,
      "scaleX": 1,
      "scaleY": 1,
      "offsetX": 0,
      "offsetY": 0,
      "skewX": 0,
      "skewY": 0
    },
    "Rectf654e4d1-ca63-4ab2-971c-497b4c0b6dd5": {
      "id": "Rectf654e4d1-ca63-4ab2-971c-497b4c0b6dd5",
      "type": "Rect",
      "stroke": "",
      "x": 2062.348966749459,
      "y": -81.75095565257283,
      "width": 100,
      "height": 100,
      "fill": "#000000",
      "ty": "Rect",
      "draggable": true,
      "rotation": 0,
      "scaleX": 1,
      "scaleY": 1,
      "offsetX": 0,
      "offsetY": 0,
      "skewX": 0,
      "skewY": 0
    },
    "Rect3ffcca28-9f33-4b2b-9875-e6449a17db34": {
      "id": "Rect3ffcca28-9f33-4b2b-9875-e6449a17db34",
      "type": "Rect",
      "stroke": "",
      "x": 1509.8163331333835,
      "y": 944.0243419281728,
      "width": 100,
      "height": 100,
      "fill": "#000000",
      "ty": "Rect",
      "draggable": true,
      "rotation": 0,
      "scaleX": 1,
      "scaleY": 1,
      "offsetX": 0,
      "offsetY": 0,
      "skewX": 0,
      "skewY": 0
    },
    "Rect86277ba5-ec38-4863-9071-b0e37b5f058c": {
      "id": "Rect86277ba5-ec38-4863-9071-b0e37b5f058c",
      "type": "Rect",
      "stroke": "",
      "x": 737.5264020563677,
      "y": 1245.1693834197679,
      "width": 100,
      "height": 100,
      "fill": "#000000",
      "ty": "Rect",
      "draggable": true,
      "rotation": 0,
      "scaleX": 1,
      "scaleY": 1,
      "offsetX": 0,
      "offsetY": 0,
      "skewX": 0,
      "skewY": 0
    },
    "Rectad0a6680-ea5a-4f37-8109-e1d04aaefea5": {
      "id": "Rectad0a6680-ea5a-4f37-8109-e1d04aaefea5",
      "type": "Rect",
      "stroke": "",
      "x": -0.23023941964339656,
      "y": 1097.7337901895082,
      "width": 100,
      "height": 100,
      "fill": "#000000",
      "ty": "Rect",
      "draggable": true,
      "rotation": 0,
      "scaleX": 1,
      "scaleY": 1,
      "offsetX": 0,
      "offsetY": 0,
      "skewX": 0,
      "skewY": 0
    },
    "Rect39431106-af67-41b3-8411-dc0363759764": {
      "id": "Rect39431106-af67-41b3-8411-dc0363759764",
      "type": "Rect",
      "stroke": "",
      "x": 2341.7546735212254,
      "y": 24.90457987570045,
      "width": 100,
      "height": 100,
      "fill": "#000000",
      "ty": "Rect",
      "draggable": true,
      "rotation": 0,
      "scaleX": 1,
      "scaleY": 1,
      "offsetX": 0,
      "offsetY": 0,
      "skewX": 0,
      "skewY": 0
    },
    "Rectedff71f7-abfa-47ef-99dd-1b6c89e377ee": {
      "id": "Rectedff71f7-abfa-47ef-99dd-1b6c89e377ee",
      "type": "Rect",
      "stroke": "",
      "x": 1556.9071825892988,
      "y": -329.56822938003137,
      "width": 100,
      "height": 100,
      "fill": "#000000",
      "ty": "Rect",
      "draggable": true,
      "rotation": 0,
      "scaleX": 1,
      "scaleY": 1,
      "offsetX": 0,
      "offsetY": 0,
      "skewX": 0,
      "skewY": 0
    },
    "Rectb448ae2f-1ebc-408d-98fa-c74c72b68466": {
      "id": "Rectb448ae2f-1ebc-408d-98fa-c74c72b68466",
      "type": "Rect",
      "stroke": "",
      "x": 1164.4834371233358,
      "y": -351.5267219887935,
      "width": 100,
      "height": 100,
      "fill": "#000000",
      "ty": "Rect",
      "draggable": true,
      "rotation": 0,
      "scaleX": 1,
      "scaleY": 1,
      "offsetX": 0,
      "offsetY": 0,
      "skewX": 0,
      "skewY": 0
    },
    "Recte2508a8a-7f80-4478-bc01-73af7ef896c4": {
      "id": "Recte2508a8a-7f80-4478-bc01-73af7ef896c4",
      "type": "Rect",
      "stroke": "",
      "x": 979.2594292634006,
      "y": -442.4976199393795,
      "width": 100,
      "height": 100,
      "fill": "#000000",
      "ty": "Rect",
      "draggable": true,
      "rotation": 0,
      "scaleX": 1,
      "scaleY": 1,
      "offsetX": 0,
      "offsetY": 0,
      "skewX": 0,
      "skewY": 0
    },
    "Rectbeee85b7-00dc-4f29-9442-13e96a2e4dd6": {
      "id": "Rectbeee85b7-00dc-4f29-9442-13e96a2e4dd6",
      "type": "Rect",
      "stroke": "",
      "x": 539.7448343415224,
      "y": 1336.1402813703537,
      "width": 100,
      "height": 100,
      "fill": "#000000",
      "ty": "Rect",
      "draggable": true,
      "rotation": 0,
      "scaleX": 1,
      "scaleY": 1,
      "offsetX": 0,
      "offsetY": 0,
      "skewX": 0,
      "skewY": 0
    },
    "Rect912ff4ef-cc15-4363-8ff8-a2b8b6900cf1": {
      "id": "Rect912ff4ef-cc15-4363-8ff8-a2b8b6900cf1",
      "type": "Rect",
      "stroke": "",
      "x": 1720.1554607031399,
      "y": 1238.8955283886928,
      "width": 100,
      "height": 100,
      "fill": "#000000",
      "ty": "Rect",
      "draggable": true,
      "rotation": 0,
      "scaleX": 1,
      "scaleY": 1,
      "offsetX": 0,
      "offsetY": 0,
      "skewX": 0,
      "skewY": 0
    },
    "Rect6d13a456-8d3f-4978-a2ef-196fc24e8571": {
      "id": "Rect6d13a456-8d3f-4978-a2ef-196fc24e8571",
      "type": "Rect",
      "stroke": "",
      "x": 1255.5257460714395,
      "y": 1213.8001082643932,
      "width": 100,
      "height": 100,
      "fill": "#000000",
      "ty": "Rect",
      "draggable": true,
      "rotation": 0,
      "scaleX": 1,
      "scaleY": 1,
      "offsetX": 0,
      "offsetY": 0,
      "skewX": 0,
      "skewY": 0
    },
    "Rect2e1230ce-c736-4845-8c1c-294e00ab4dba": {
      "id": "Rect2e1230ce-c736-4845-8c1c-294e00ab4dba",
      "type": "Rect",
      "stroke": "",
      "x": 2878.863484245508,
      "y": 1047.8848750401023,
      "width": 100,
      "height": 100,
      "fill": "#000000",
      "ty": "Rect",
      "draggable": true,
      "rotation": 0,
      "scaleX": 1,
      "scaleY": 1,
      "offsetX": 0,
      "offsetY": 0,
      "skewX": 0,
      "skewY": 0
    },
    "Recta710bc8f-5cde-4dc1-b228-60dc846e94e6": {
      "id": "Recta710bc8f-5cde-4dc1-b228-60dc846e94e6",
      "type": "Rect",
      "stroke": "",
      "x": -367.85280417215773,
      "y": 1465.409927358137,
      "width": 100,
      "height": 100,
      "fill": "#000000",
      "ty": "Rect",
      "draggable": true,
      "rotation": 0,
      "scaleX": 1,
      "scaleY": 1,
      "offsetX": 0,
      "offsetY": 0,
      "skewX": 0,
      "skewY": 0
    },
    "Rect33e5eeff-fed6-41ad-94cc-2ab8e632f6a2": {
      "id": "Rect33e5eeff-fed6-41ad-94cc-2ab8e632f6a2",
      "type": "Rect",
      "stroke": "",
      "x": 2862.149372078622,
      "y": -33.50501046360705,
      "width": 100,
      "height": 100,
      "fill": "#000000",
      "ty": "Rect",
      "draggable": true,
      "rotation": 0,
      "scaleX": 1,
      "scaleY": 1,
      "offsetX": 0,
      "offsetY": 0,
      "skewX": 0,
      "skewY": 0
    },
    "Rect57dba0d7-b0f2-4d54-835f-5d31d5f7d282": {
      "id": "Rect57dba0d7-b0f2-4d54-835f-5d31d5f7d282",
      "type": "Rect",
      "stroke": "",
      "x": -417.9951406728168,
      "y": 805.7203446956427,
      "width": 100,
      "height": 100,
      "fill": "#000000",
      "ty": "Rect",
      "draggable": true,
      "rotation": 0,
      "scaleX": 1,
      "scaleY": 1,
      "offsetX": 0,
      "offsetY": 0,
      "skewX": 0,
      "skewY": 0
    },
    "Rect86115767-565f-4647-8095-c0c6c3343451": {
      "id": "Rect86115767-565f-4647-8095-c0c6c3343451",
      "type": "Rect",
      "stroke": "",
      "x": 2891.3990683706725,
      "y": 321.39128400672246,
      "width": 100,
      "height": 100,
      "fill": "#000000",
      "ty": "Rect",
      "draggable": true,
      "rotation": 0,
      "scaleX": 1,
      "scaleY": 1,
      "offsetX": 0,
      "offsetY": 0,
      "skewX": 0,
      "skewY": 0
    },
    "Rect4be792f2-a097-4dc3-85e3-9a16fea310ae": {
      "id": "Rect4be792f2-a097-4dc3-85e3-9a16fea310ae",
      "type": "Rect",
      "stroke": "",
      "x": 2473.546264198515,
      "y": 1298.3999064309235,
      "width": 100,
      "height": 100,
      "fill": "#000000",
      "ty": "Rect",
      "draggable": true,
      "rotation": 0,
      "scaleX": 1,
      "scaleY": 1,
      "offsetX": 0,
      "offsetY": 0,
      "skewX": 0,
      "skewY": 0
    },
    "Rected51a7d6-e328-4c22-9606-bb967fb26862": {
      "id": "Rected51a7d6-e328-4c22-9606-bb967fb26862",
      "type": "Rect",
      "stroke": "",
      "x": 3472.214466169972,
      "y": 463.349801794854,
      "width": 100,
      "height": 100,
      "fill": "#000000",
      "ty": "Rect",
      "draggable": true,
      "rotation": 0,
      "scaleX": 1,
      "scaleY": 1,
      "offsetX": 0,
      "offsetY": 0,
      "skewX": 0,
      "skewY": 0
    },
    "Rect74a7dc41-12f5-4b5a-a999-3b8466e22227": {
      "id": "Rect74a7dc41-12f5-4b5a-a999-3b8466e22227",
      "type": "Rect",
      "stroke": "",
      "x": 5219.526555472456,
      "y": 1468.2123555092958,
      "width": 100,
      "height": 100,
      "fill": "#000000",
      "ty": "Rect",
      "draggable": true,
      "rotation": 0,
      "scaleX": 1,
      "scaleY": 1,
      "offsetX": 0,
      "offsetY": 0,
      "skewX": 0,
      "skewY": 0
    },
    "Rectd54a18ce-c72e-4fac-a2c6-9457e25ea82b": {
      "id": "Rectd54a18ce-c72e-4fac-a2c6-9457e25ea82b",
      "type": "Rect",
      "stroke": "",
      "x": 4687.279442660499,
      "y": -329.0050260412776,
      "width": 100,
      "height": 100,
      "fill": "#000000",
      "ty": "Rect",
      "draggable": true,
      "rotation": 0,
      "scaleX": 1,
      "scaleY": 1,
      "offsetX": 0,
      "offsetY": 0,
      "skewX": 0,
      "skewY": 0
    },
    "Recte494236d-6a9c-433b-a9e7-6e2557b3abcc": {
      "id": "Recte494236d-6a9c-433b-a9e7-6e2557b3abcc",
      "type": "Rect",
      "stroke": "",
      "x": 4179.503461472081,
      "y": 2134.5276432270252,
      "width": 100,
      "height": 100,
      "fill": "#000000",
      "ty": "Rect",
      "draggable": true,
      "rotation": 0,
      "scaleX": 1,
      "scaleY": 1,
      "offsetX": 0,
      "offsetY": 0,
      "skewX": 0,
      "skewY": 0
    },
    "Rect5ac50e7b-19fc-4461-8be4-4574cf7cd4fb": {
      "id": "Rect5ac50e7b-19fc-4461-8be4-4574cf7cd4fb",
      "type": "Rect",
      "stroke": "",
      "x": 1897.5704375771386,
      "y": 1957.2510987883636,
      "width": 100,
      "height": 100,
      "fill": "#000000",
      "ty": "Rect",
      "draggable": true,
      "rotation": 0,
      "scaleX": 1,
      "scaleY": 1,
      "offsetX": 0,
      "offsetY": 0,
      "skewX": 0,
      "skewY": 0
    },
    "Rect310443e1-a8e5-488f-adea-5fd3dfb2acf8": {
      "id": "Rect310443e1-a8e5-488f-adea-5fd3dfb2acf8",
      "type": "Rect",
      "stroke": "",
      "x": 716.8383367414172,
      "y": 1951.138114497375,
      "width": 100,
      "height": 100,
      "fill": "#000000",
      "ty": "Rect",
      "draggable": true,
      "rotation": 0,
      "scaleX": 1,
      "scaleY": 1,
      "offsetX": 0,
      "offsetY": 0,
      "skewX": 0,
      "skewY": 0
    },
    "RegularPolygon3139da92-c94d-4352-9c01-49c269229dd7": {
      "id": "RegularPolygon3139da92-c94d-4352-9c01-49c269229dd7",
      "type": "RegularPolygon",
      "stroke": "",
      "x": -757.5473435767624,
      "y": 2128.414658936037,
      "sides": 3,
      "radius": 50,
      "fill": "#000000",
      "ty": "RegularPolygon",
      "draggable": true,
      "rotation": 0,
      "scaleX": 1,
      "scaleY": 1,
      "offsetX": 0,
      "offsetY": 0,
      "skewX": 0,
      "skewY": 0
    },
    "RegularPolygon6ef64cde-02c1-4b78-ab0d-93fb505a8eed": {
      "id": "RegularPolygon6ef64cde-02c1-4b78-ab0d-93fb505a8eed",
      "type": "RegularPolygon",
      "stroke": "",
      "x": -2556.1755179068246,
      "y": 178.37267011075505,
      "sides": 3,
      "radius": 50,
      "fill": "#000000",
      "ty": "RegularPolygon",
      "draggable": true,
      "rotation": 0,
      "scaleX": 1,
      "scaleY": 1,
      "offsetX": 0,
      "offsetY": 0,
      "skewX": 0,
      "skewY": 0
    },
    "Rect48": {
      "id": "Rect48",
      "type": "Rect",
      "stroke": "",
      "x": 852.2457257859047,
      "y": 72.98900092559771,
      "width": 100,
      "height": 100,
      "fill": "#000000",
      "ty": "Shape",
      "draggable": true,
      "rotation": 0,
      "scaleX": 1,
      "scaleY": 1,
      "offsetX": 0,
      "offsetY": 0,
      "skewX": 0,
      "skewY": 0
    }
  }
},
{
  "_id": 3,
  "templateId": "bubbleChat",
  "projectName": "btest",
  "thumbnail": "https://getidea-s3.s3.ap-northeast-2.amazonaws.com/thumbnailImage/bubbleChat.png",
  "lastUpdateTime": {
    "$date": "2024-02-15T11:47:11.358Z"
  },
  "data": {
    "Circle1": {
      "id": "Circle1",
      "type": "Circle",
      "stroke": "",
      "x": 40.99821958456974,
      "y": 168.04127317243794,
      "radius": 50,
      "fill": "#000000",
      "ty": "Shape",
      "draggable": true,
      "rotation": 0,
      "scaleX": 1,
      "scaleY": 1,
      "offsetX": 0,
      "offsetY": 0,
      "skewX": 0,
      "skewY": 0
    },
    "Arrow3": {
      "id": "Arrow3",
      "points": [
        null,
        null,
        null,
        null
      ],
      "pointerLength": 20,
      "stroke": "#000000",
      "rotation": 0,
      "strokeWidth": 10,
      "fill": "#000000",
      "ty": "Line",
      "type": "Arrow",
      "lineJoin": "round",
      "x": 259.05123639960436,
      "y": 218.0762504372158,
      "draggable": true,
      "dashEnabled": true,
      "scaleX": 1,
      "scaleY": 1,
      "offsetX": 0,
      "offsetY": 0,
      "skewX": 0,
      "skewY": 0
    },
    "Arrow4": {
      "id": "Arrow4",
      "points": [
        null,
        null,
        null,
        null
      ],
      "pointerLength": 20,
      "stroke": "#000000",
      "rotation": 0,
      "strokeWidth": 10,
      "fill": "#000000",
      "ty": "Line",
      "type": "Arrow",
      "lineJoin": "round",
      "x": 225.04451038575667,
      "y": 186.0650577124869,
      "draggable": true,
      "dashEnabled": true,
      "scaleX": 1,
      "scaleY": 1,
      "offsetX": 0,
      "offsetY": 0,
      "skewX": 0,
      "skewY": 0
    }
  }
},
{
  "_id": 4,
  "templateId": "sixhat",
  "projectName": "6test",
  "thumbnail": "https://getidea-s3.s3.ap-northeast-2.amazonaws.com/thumbnailImage/sixhat.png",
  "lastUpdateTime": {
    "$date": "2024-02-13T11:33:23.695Z"
  },
  "data": {}
},
{
  "_id": 5,
  "templateId": "7check",
  "projectName": "7c",
  "thumbnail": "https://getidea-s3.s3.ap-northeast-2.amazonaws.com/thumbnailImage/7Check.png",
  "lastUpdateTime": {
    "$date": "2024-02-15T11:44:09.120Z"
  },
  "data": {
    "Rect1": {
      "id": "Rect1",
      "type": "Rect",
      "stroke": "",
      "x": 292.0478733926804,
      "y": 267.80731184047323,
      "width": 71.8692673657366,
      "height": 71.86926736573662,
      "fill": "#000000",
      "ty": "Shape",
      "draggable": true,
      "rotation": 0,
      "scaleX": 1,
      "scaleY": 1,
      "offsetX": 0,
      "offsetY": 0,
      "skewX": 0,
      "skewY": 0
    },
    "Circle2": {
      "id": "Circle2",
      "type": "Circle",
      "stroke": "",
      "x": 975.1829871414441,
      "y": 300.9854753775823,
      "radius": 50,
      "fill": "#000000",
      "ty": "Shape",
      "draggable": true,
      "rotation": 0,
      "scaleX": 1,
      "scaleY": 1,
      "offsetX": 0,
      "offsetY": 0,
      "skewX": 0,
      "skewY": 0
    },
    "Text-1": {
      "id": "Text-1",
      "text": "대체 ㄱㄱ",
      "x": 376.5129358573354,
      "y": 101.36378092249943,
      "ty": "Text",
      "draggable": true,
      "style": {
        "zIndex": 100
      },
      "fill": "black",
      "rotation": 0,
      "scaleX": 1,
      "scaleY": 1,
      "offsetX": 0,
      "offsetY": 0,
      "skewX": 0,
      "skewY": 0
    }
  }
},
{
  "_id": 6,
  "templateId": "bubbleChat",
  "projectName": "chat",
  "thumbnail": "https://getidea-s3.s3.ap-northeast-2.amazonaws.com/thumbnailImage/bubbleChat.png",
  "lastUpdateTime": {
    "$date": "2024-02-13T15:29:29.931Z"
  },
  "data": {}
},
{
  "_id": 7,
  "templateId": "sixhat",
  "projectName": "test",
  "thumbnail": "https://getidea-s3.s3.ap-northeast-2.amazonaws.com/thumbnailImage/sixhat.png",
  "lastUpdateTime": {
    "$date": "2024-02-13T15:29:40.863Z"
  },
  "data": {}
},
{
  "_id": 8,
  "templateId": "7check",
  "projectName": "7check",
  "thumbnail": "https://getidea-s3.s3.ap-northeast-2.amazonaws.com/thumbnailImage/7Check.png",
  "lastUpdateTime": {
    "$date": "2024-02-13T15:29:50.574Z"
  },
  "data": {}
},
{
  "_id": 9,
  "templateId": "whiteboard",
  "projectName": "whiteboard",
  "thumbnail": "https://getidea-s3.s3.ap-northeast-2.amazonaws.com/thumbnailImage/whiteboard.png",
  "lastUpdateTime": {
    "$date": "2024-02-13T15:30:00.118Z"
  },
  "data": {}
},
{
  "_id": 11,
  "templateId": "bubbleChat",
  "projectName": "프로젝트 이미지",
  "thumbnail": "https://getidea-s3.s3.ap-northeast-2.amazonaws.com/thumbnailImage/bubbleChat.png",
  "lastUpdateTime": {
    "$date": "2024-02-14T11:05:46.856Z"
  },
  "data": {}
},
{
  "_id": 12,
  "templateId": "whiteboard",
  "projectName": "ㅋㅋㅋㅋ",
  "thumbnail": "https://getidea-s3.s3.ap-northeast-2.amazonaws.com/thumbnailImage/whiteboard.png",
  "lastUpdateTime": {
    "$date": "2024-02-14T00:53:44.934Z"
  },
  "data": {}
},
{
  "_id": 13,
  "templateId": "bubbleChat",
  "projectName": "ㅋㅋㅋㅋㅋㅋㅋㅋ",
  "thumbnail": "https://getidea-s3.s3.ap-northeast-2.amazonaws.com/thumbnailImage/bubbleChat.png",
  "lastUpdateTime": {
    "$date": "2024-02-14T01:00:56.222Z"
  },
  "data": {}
},
{
  "_id": 14,
  "templateId": "bubbleChat",
  "projectName": "gd",
  "thumbnail": "https://getidea-s3.s3.ap-northeast-2.amazonaws.com/thumbnailImage/bubbleChat.png",
  "lastUpdateTime": {
    "$date": "2024-02-14T01:05:17.669Z"
  },
  "data": {}
},
{
  "_id": 15,
  "templateId": "whiteboard",
  "projectName": "화이트보드",
  "thumbnail": "https://getidea-s3.s3.ap-northeast-2.amazonaws.com/thumbnailImage/whiteboard.png",
  "lastUpdateTime": {
    "$date": "2024-02-14T01:15:17.527Z"
  },
  "data": {}
},
{
  "_id": 16,
  "templateId": "7check",
  "projectName": "7첵",
  "thumbnail": "https://getidea-s3.s3.ap-northeast-2.amazonaws.com/thumbnailImage/7Check.png",
  "lastUpdateTime": {
    "$date": "2024-02-14T01:19:02.076Z"
  },
  "data": {}
},
{
  "_id": 17,
  "templateId": "sixhat",
  "projectName": "6생모",
  "thumbnail": "https://getidea-s3.s3.ap-northeast-2.amazonaws.com/thumbnailImage/sixhat.png",
  "lastUpdateTime": {
    "$date": "2024-02-14T01:19:11.894Z"
  },
  "data": {}
},
{
  "_id": 18,
  "templateId": "bubbleChat",
  "projectName": "아이디어말풍선선선선",
  "thumbnail": "https://getidea-s3.s3.ap-northeast-2.amazonaws.com/thumbnailImage/bubbleChat.png",
  "lastUpdateTime": {
    "$date": "2024-02-14T01:20:09.279Z"
  },
  "data": {}
},
{
  "_id": 19,
  "templateId": "whiteboard",
  "projectName": "화이트보드보드",
  "thumbnail": "https://getidea-s3.s3.ap-northeast-2.amazonaws.com/thumbnailImage/whiteboard.png",
  "lastUpdateTime": {
    "$date": "2024-02-14T01:20:31.323Z"
  },
  "data": {}
},
{
  "_id": 20,
  "templateId": "sixhat",
  "projectName": "6생",
  "thumbnail": "https://getidea-s3.s3.ap-northeast-2.amazonaws.com/thumbnailImage/sixhat.png",
  "lastUpdateTime": {
    "$date": "2024-02-14T01:21:14.560Z"
  },
  "data": {}
},
{
  "_id": 21,
  "templateId": "whiteboard",
  "projectName": "화이트보드보드보",
  "thumbnail": "https://getidea-s3.s3.ap-northeast-2.amazonaws.com/thumbnailImage/whiteboard.png",
  "lastUpdateTime": {
    "$date": "2024-02-14T01:21:26.235Z"
  },
  "data": {}
},
{
  "_id": 22,
  "templateId": "bubbleChat",
  "projectName": "ㅇㄹㅇㄹㅇㄹㅇㄹ",
  "thumbnail": "https://getidea-s3.s3.ap-northeast-2.amazonaws.com/thumbnailImage/bubbleChat.png",
  "lastUpdateTime": {
    "$date": "2024-02-14T01:22:43.600Z"
  },
  "data": {}
},
{
  "_id": 23,
  "templateId": "sixhat",
  "projectName": "ddd",
  "thumbnail": "https://getidea-s3.s3.ap-northeast-2.amazonaws.com/thumbnailImage/sixhat.png",
  "lastUpdateTime": {
    "$date": "2024-02-15T11:44:02.615Z"
  },
  "data": {
    "Rect1": {
      "id": "Rect1",
      "type": "Rect",
      "stroke": "",
      "x": 720.2052821403444,
      "y": 257.90053010975333,
      "width": 100,
      "height": 100,
      "fill": "#000000",
      "ty": "Shape",
      "draggable": true,
      "rotation": 0,
      "scaleX": 1,
      "scaleY": 1,
      "offsetX": 0,
      "offsetY": 0,
      "skewX": 0,
      "skewY": 0
    }
  }
},
{
  "_id": 24,
  "templateId": "sixhat",
  "projectName": "zzzzzz",
  "thumbnail": "https://getidea-s3.s3.ap-northeast-2.amazonaws.com/thumbnailImage/sixhat.png",
  "lastUpdateTime": {
    "$date": "2024-02-14T01:24:50.848Z"
  },
  "data": {}
},
{
  "_id": 26,
  "templateId": "sixhat",
  "projectName": "hats",
  "thumbnail": "https://getidea-s3.s3.ap-northeast-2.amazonaws.com/thumbnailImage/sixhat.png",
  "lastUpdateTime": {
    "$date": "2024-02-14T01:42:51.499Z"
  },
  "data": {}
},
{
  "_id": 27,
  "templateId": "sixhat",
  "projectName": "dea-hat",
  "thumbnail": "https://getidea-s3.s3.ap-northeast-2.amazonaws.com/thumbnailImage/sixhat.png",
  "lastUpdateTime": {
    "$date": "2024-02-14T01:47:59.024Z"
  },
  "data": {}
},
{
  "_id": 28,
  "templateId": "whiteboard",
  "projectName": "화이트",
  "thumbnail": "https://getidea-s3.s3.ap-northeast-2.amazonaws.com/thumbnailImage/whiteboard.png",
  "lastUpdateTime": {
    "$date": "2024-02-14T03:13:23.019Z"
  },
  "data": {}
},
{
  "_id": 29,
  "templateId": "whiteboard",
  "projectName": "ㅋㅋㅋㅋ",
  "thumbnail": "https://getidea-s3.s3.ap-northeast-2.amazonaws.com/thumbnailImage/whiteboard.png",
  "lastUpdateTime": {
    "$date": "2024-02-14T11:11:55.616Z"
  },
  "data": {}
},
{
  "_id": 30,
  "templateId": "whiteboard",
  "projectName": "강준규",
  "thumbnail": "https://getidea-s3.s3.ap-northeast-2.amazonaws.com/thumbnailImage/whiteboard.png",
  "lastUpdateTime": {
    "$date": "2024-02-14T05:12:36.300Z"
  },
  "data": {}
},
{
  "_id": 31,
  "templateId": "whiteboard",
  "projectName": "228",
  "thumbnail": "https://getidea-s3.s3.ap-northeast-2.amazonaws.com/thumbnailImage/whiteboard.png",
  "lastUpdateTime": {
    "$date": "2024-02-14T10:45:18.147Z"
  },
  "data": {}
},
{
  "_id": 32,
  "templateId": "whiteboard",
  "projectName": "가나다라마바사",
  "thumbnail": "https://getidea-s3.s3.ap-northeast-2.amazonaws.com/thumbnailImage/whiteboard.png",
  "lastUpdateTime": {
    "$date": "2024-02-14T10:31:35.103Z"
  },
  "data": {}
},
{
  "_id": 33,
  "templateId": "whiteboard",
  "projectName": "아하",
  "thumbnail": "https://getidea-s3.s3.ap-northeast-2.amazonaws.com/thumbnailImage/whiteboard.png",
  "lastUpdateTime": {
    "$date": "2024-02-15T13:12:25.036Z"
  },
  "data": {
    "Rect04adfaf5-e6bc-4d00-b7b4-241f9c19de0c": {
      "id": "Rect04adfaf5-e6bc-4d00-b7b4-241f9c19de0c",
      "type": "Rect",
      "stroke": "",
      "strokeWidth": 3,
      "x": 634.1789324924791,
      "y": 91.97991473370017,
      "width": 100,
      "height": 100,
      "fill": "#000000",
      "ty": "Rect",
      "draggable": true,
      "rotation": 0,
      "scaleX": 1,
      "scaleY": 1,
      "offsetX": 0,
      "offsetY": 0,
      "skewX": 0,
      "skewY": 0
    },
    "image81615eba-f5bb-483d-b0de-05da266af0dc": {
      "id": "image81615eba-f5bb-483d-b0de-05da266af0dc",
      "src": "/img/template1_bubble_chat/bubble_chat1.svg",
      "x": 599.1682087985807,
      "y": 455.61820600330833,
      "ty": "Image",
      "type": "Image",
      "image": {},
      "width": 135.13513513513513,
      "height": 200,
      "draggable": true,
      "rotation": 0,
      "scaleX": 1,
      "scaleY": 1,
      "offsetX": 0,
      "offsetY": 0,
      "skewX": 0,
      "skewY": 0
    },
    "imaged155b918-023d-4b52-aa26-2a6ed0fa1fec": {
      "id": "imaged155b918-023d-4b52-aa26-2a6ed0fa1fec",
      "src": "/img/template1_bubble_chat/bubble_chat18.svg",
      "x": 423.1142839378336,
      "y": 351.85557737089187,
      "ty": "Image",
      "type": "Image",
      "image": {},
      "width": 200,
      "height": 175.5,
      "draggable": true,
      "rotation": 0,
      "scaleX": 1,
      "scaleY": 1,
      "offsetX": 0,
      "offsetY": 0,
      "skewX": 0,
      "skewY": 0
    },
    "RegularPolygon2": {
      "id": "RegularPolygon2",
      "type": "RegularPolygon",
      "stroke": "",
      "x": 674.1911881426491,
      "y": 325.8680111071727,
      "sides": 3,
      "radius": 50,
      "fill": "#000000",
      "ty": "Shape",
      "draggable": true,
      "rotation": 0,
      "scaleX": 1,
      "scaleY": 1,
      "offsetX": 0,
      "offsetY": 0,
      "skewX": 0,
      "skewY": 0
    },
    "Circle3": {
      "id": "Circle3",
      "type": "Circle",
      "stroke": "",
      "x": 501.13818245566466,
      "y": 132.96030768802657,
      "radius": 50,
      "fill": "#000000",
      "ty": "Shape",
      "draggable": true,
      "rotation": 0,
      "scaleX": 1,
      "scaleY": 1,
      "offsetX": 0,
      "offsetY": 0,
      "skewX": 0,
      "skewY": 0
    },
    "Rect4": {
      "id": "Rect4",
      "type": "Rect",
      "stroke": "",
      "x": 94.11689631393637,
      "y": 625.5354615283586,
      "width": 100,
      "height": 100,
      "fill": "#000000",
      "ty": "Shape",
      "draggable": true,
      "rotation": 0,
      "scaleX": 1,
      "scaleY": 1,
      "offsetX": 0,
      "offsetY": 0,
      "skewX": 0,
      "skewY": 0
    },
    "Circle5": {
      "id": "Circle5",
      "type": "Circle",
      "stroke": "",
      "x": 252.41870073453168,
      "y": 249.62266007965593,
      "radius": 50,
      "fill": "#000000",
      "ty": "Shape",
      "draggable": true,
      "rotation": 0,
      "scaleX": 1,
      "scaleY": 1,
      "offsetX": 0,
      "offsetY": 0,
      "skewX": 0,
      "skewY": 0
    },
    "Circlecd4e9a7d-ece9-4b7a-9698-a25fe01ff85e": {
      "id": "Circlecd4e9a7d-ece9-4b7a-9698-a25fe01ff85e",
      "type": "Circle",
      "stroke": "#000000",
      "strokeWidth": 3,
      "x": 348.09130459376513,
      "y": 127.96269879115752,
      "radius": 50,
      "fill": "#ffffff",
      "ty": "Circle",
      "draggable": true,
      "rotation": 0,
      "scaleX": 1,
      "scaleY": 1,
      "offsetX": 0,
      "offsetY": 0,
      "skewX": 0,
      "skewY": 0
    },
    "Rect14993bd5-5ed9-441d-8945-5a6babc35385": {
      "id": "Rect14993bd5-5ed9-441d-8945-5a6babc35385",
      "type": "Rect",
      "stroke": "#000000",
      "strokeWidth": 3,
      "x": 171.0370733417637,
      "y": 229.91392028728654,
      "width": 100,
      "height": 100,
      "fill": "#ffffff",
      "ty": "Rect",
      "draggable": true,
      "rotation": 0,
      "scaleX": 1,
      "scaleY": 1,
      "offsetX": 0,
      "offsetY": 0,
      "skewX": 0,
      "skewY": 0
    },
    "imagecbbd7fa6-3889-4828-9cc6-b6c6ae879aeb": {
      "id": "imagecbbd7fa6-3889-4828-9cc6-b6c6ae879aeb",
      "src": "/img/template1_bubble_chat/bubble_chat2.svg",
      "x": 634.1789324924792,
      "y": 187.9340055535864,
      "ty": "Image",
      "type": "Image",
      "image": {},
      "width": 200,
      "height": 175.5,
      "draggable": true,
      "rotation": 0,
      "scaleX": 1,
      "scaleY": 1,
      "offsetX": 0,
      "offsetY": 0,
      "skewX": 0,
      "skewY": 0
    }
  }
},
{
  "_id": 35,
  "templateId": "whiteboard",
  "projectName": "test",
  "thumbnail": "https://getidea-s3.s3.ap-northeast-2.amazonaws.com/thumbnailImage/whiteboard.png",
  "lastUpdateTime": {
    "$date": "2024-02-14T13:15:20.394Z"
  },
  "data": {}
},
{
  "_id": 36,
  "templateId": "whiteboard",
  "projectName": "이건진짜다",
  "thumbnail": "https://getidea-s3.s3.ap-northeast-2.amazonaws.com/thumbnailImage/whiteboard.png",
  "lastUpdateTime": {
    "$date": "2024-02-14T13:37:05.759Z"
  },
  "data": {}
},
{
  "_id": 37,
  "templateId": "bubbleChat",
  "projectName": "0215",
  "thumbnail": "https://getidea-s3.s3.ap-northeast-2.amazonaws.com/thumbnailImage/bubbleChat.png",
  "lastUpdateTime": {
    "$date": "2024-02-15T11:43:27.249Z"
  },
  "data": {
    "RegularPolygon1": {
      "id": "RegularPolygon1",
      "type": "RegularPolygon",
      "stroke": "",
      "x": 622.1752557974283,
      "y": 275.2032520325203,
      "sides": 3,
      "radius": 50,
      "fill": "#000000",
      "ty": "Shape",
      "draggable": true,
      "rotation": 0,
      "scaleX": 1,
      "scaleY": 1,
      "offsetX": 0,
      "offsetY": 0,
      "skewX": 0,
      "skewY": 0
    }
  }
},
{
  "_id": 38,
  "templateId": "bubbleChat",
  "projectName": "test",
  "thumbnail": "https://getidea-s3.s3.ap-northeast-2.amazonaws.com/thumbnailImage/bubbleChat.png",
  "lastUpdateTime": {
    "$date": "2024-02-15T01:13:31.063Z"
  },
  "data": {}
},
{
  "_id": 39,
  "templateId": "bubbleChat",
  "projectName": "realtest",
  "thumbnail": "https://getidea-s3.s3.ap-northeast-2.amazonaws.com/thumbnailImage/bubbleChat.png",
  "lastUpdateTime": {
    "$date": "2024-02-15T02:07:23.593Z"
  },
  "data": {}
},
{
  "_id": 40,
  "templateId": "sixhat",
  "projectName": "템플릿2",
  "thumbnail": "https://getidea-s3.s3.ap-northeast-2.amazonaws.com/thumbnailImage/sixhat.png",
  "lastUpdateTime": {
    "$date": "2024-02-15T02:58:15.458Z"
  },
  "data": {}
},
{
  "_id": 41,
  "templateId": "bubbleChat",
  "projectName": "bzeromo",
  "thumbnail": "https://getidea-s3.s3.ap-northeast-2.amazonaws.com/thumbnailImage/bubbleChat.png",
  "lastUpdateTime": {
    "$date": "2024-02-15T05:43:02.154Z"
  },
  "data": {}
},
{
  "_id": 42,
  "templateId": "sixhat",
  "projectName": "good",
  "thumbnail": "https://getidea-s3.s3.ap-northeast-2.amazonaws.com/thumbnailImage/sixhat.png",
  "lastUpdateTime": {
    "$date": "2024-02-15T05:44:25.456Z"
  },
  "data": {}
},
{
  "_id": 43,
  "templateId": "bubbleChat",
  "projectName": "dddd",
  "thumbnail": "https://getidea-s3.s3.ap-northeast-2.amazonaws.com/thumbnailImage/bubbleChat.png",
  "lastUpdateTime": {
    "$date": "2024-02-15T05:45:12.196Z"
  },
  "data": {}
},
{
  "_id": 44,
  "templateId": "whiteboard",
  "projectName": "gg",
  "thumbnail": "https://getidea-s3.s3.ap-northeast-2.amazonaws.com/thumbnailImage/whiteboard.png",
  "lastUpdateTime": {
    "$date": "2024-02-15T05:54:10.271Z"
  },
  "data": {}
},
{
  "_id": 45,
  "templateId": "7check",
  "projectName": "yg5260",
  "thumbnail": "https://getidea-s3.s3.ap-northeast-2.amazonaws.com/thumbnailImage/7Check.png",
  "lastUpdateTime": {
    "$date": "2024-02-15T05:56:20.845Z"
  },
  "data": {}
},
{
  "_id": 46,
  "templateId": "sixhat",
  "projectName": "ㅇㅇㅇㄹㅇㄹㅇㄹ",
  "thumbnail": "https://getidea-s3.s3.ap-northeast-2.amazonaws.com/thumbnailImage/sixhat.png",
  "lastUpdateTime": {
    "$date": "2024-02-15T05:58:35.002Z"
  },
  "data": {}
},
{
  "_id": 47,
  "templateId": "sixhat",
  "projectName": "gfgf",
  "thumbnail": "https://getidea-s3.s3.ap-northeast-2.amazonaws.com/thumbnailImage/sixhat.png",
  "lastUpdateTime": {
    "$date": "2024-02-15T08:36:07.387Z"
  },
  "data": {
    "Text-1": {
      "id": "Text-1",
      "text": "OH GOOD",
      "x": 265.081193682375,
      "y": 222.16718720107403,
      "ty": "Text",
      "draggable": true,
      "style": {
        "zIndex": 100
      },
      "fill": "black",
      "rotation": 0,
      "scaleX": 1,
      "scaleY": 1,
      "offsetX": 0,
      "offsetY": 0,
      "skewX": 0,
      "skewY": 0
    }
  }
},
{
  "_id": 48,
  "templateId": "whiteboard",
  "projectName": "holy",
  "thumbnail": "https://getidea-s3.s3.ap-northeast-2.amazonaws.com/thumbnailImage/whiteboard.png",
  "lastUpdateTime": {
    "$date": "2024-02-15T06:24:34.072Z"
  },
  "data": {}
},
{
  "_id": 49,
  "templateId": "whiteboard",
  "projectName": "dhodfkmw",
  "thumbnail": "https://getidea-s3.s3.ap-northeast-2.amazonaws.com/thumbnailImage/whiteboard.png",
  "lastUpdateTime": {
    "$date": "2024-02-15T06:25:58.936Z"
  },
  "data": {}
},
{
  "_id": 50,
  "templateId": "whiteboard",
  "projectName": "dsds",
  "thumbnail": "https://getidea-s3.s3.ap-northeast-2.amazonaws.com/thumbnailImage/whiteboard.png",
  "lastUpdateTime": {
    "$date": "2024-02-15T06:26:36.880Z"
  },
  "data": {}
},
{
  "_id": 51,
  "templateId": "whiteboard",
  "projectName": "zzz",
  "thumbnail": "https://getidea-s3.s3.ap-northeast-2.amazonaws.com/thumbnailImage/whiteboard.png",
  "lastUpdateTime": {
    "$date": "2024-02-15T06:59:15.946Z"
  },
  "data": {
    "Rect87610eb9-f115-4a12-bc69-fd40b45f8360": {
      "id": "Rect87610eb9-f115-4a12-bc69-fd40b45f8360",
      "type": "Rect",
      "stroke": "",
      "strokeWidth": 3,
      "x": 449.1222501104439,
      "y": 159.94739573111957,
      "width": 100,
      "height": 100,
      "fill": "#000000",
      "ty": "Rect",
      "draggable": true,
      "rotation": 0,
      "scaleX": 1,
      "scaleY": 1,
      "offsetX": 0,
      "offsetY": 0,
      "skewX": 0,
      "skewY": 0
    },
    "RegularPolygon8f348b0a-1a6d-4465-aa59-e1196b1669ec": {
      "id": "RegularPolygon8f348b0a-1a6d-4465-aa59-e1196b1669ec",
      "type": "RegularPolygon",
      "stroke": "",
      "strokeWidth": 3,
      "x": 722.2058949228528,
      "y": 357.85270804713474,
      "sides": 3,
      "radius": 50,
      "fill": "#000000",
      "ty": "RegularPolygon",
      "draggable": true,
      "rotation": 0,
      "scaleX": 1,
      "scaleY": 1,
      "offsetX": 0,
      "offsetY": 0,
      "skewX": 0,
      "skewY": 0
    },
    "Linef686c1a4-0d89-422b-854e-94c5d69524a5": {
      "id": "Linef686c1a4-0d89-422b-854e-94c5d69524a5",
      "points": [
        50,
        50,
        250,
        50
      ],
      "stroke": "#000000",
      "strokeWidth": 10,
      "rotation": 0,
      "lineCap": "round",
      "lineJoin": "round",
      "fill": "#000000",
      "ty": "Line",
      "type": "Line",
      "x": 313.0805808998665,
      "y": 318.871358651556,
      "draggable": true,
      "scaleX": 1,
      "scaleY": 1,
      "offsetX": 0,
      "offsetY": 0,
      "skewX": 0,
      "skewY": 0
    }
  }
},
{
  "_id": 52,
  "templateId": "sixhat",
  "projectName": "6생",
  "thumbnail": "https://getidea-s3.s3.ap-northeast-2.amazonaws.com/thumbnailImage/sixhat.png",
  "lastUpdateTime": {
    "$date": "2024-02-15T11:43:08.361Z"
  },
  "data": {
    "Rect4f47aa11-2751-49f6-b312-3a065a2156cf": {
      "id": "Rect4f47aa11-2751-49f6-b312-3a065a2156cf",
      "type": "Rect",
      "stroke": "",
      "strokeWidth": 3,
      "x": 75.00765978135603,
      "y": 242.90770341914617,
      "width": 100,
      "height": 100,
      "fill": "#000000",
      "ty": "Rect",
      "draggable": true,
      "rotation": 0,
      "scaleX": 1,
      "scaleY": 1,
      "offsetX": 0,
      "offsetY": 0,
      "skewX": 0,
      "skewY": 0
    },
    "Circle49fec561-6a12-47fe-a63f-65f451244fb7": {
      "id": "Circle49fec561-6a12-47fe-a63f-65f451244fb7",
      "type": "Circle",
      "stroke": "",
      "strokeWidth": 3,
      "x": 865.24970887221,
      "y": 283.8880963734726,
      "radius": 50,
      "fill": "#000000",
      "ty": "Circle",
      "draggable": true,
      "rotation": 0,
      "scaleX": 1,
      "scaleY": 1,
      "offsetX": 0,
      "offsetY": 0,
      "skewX": 0,
      "skewY": 0
    },
    "Circlec2901f58-cb1e-426f-9eaf-98c794b22f6c": {
      "id": "Circlec2901f58-cb1e-426f-9eaf-98c794b22f6c",
      "type": "Circle",
      "stroke": "",
      "strokeWidth": 3,
      "x": 530.1470678020378,
      "y": 257.90053010975333,
      "radius": 50,
      "fill": "#000000",
      "ty": "Circle",
      "draggable": true,
      "rotation": 0,
      "scaleX": 1,
      "scaleY": 1,
      "offsetX": 0,
      "offsetY": 0,
      "skewX": 0,
      "skewY": 0
    },
    "Circle29738b1b-2cff-4d8b-b3f6-58e38f2a4dc6": {
      "id": "Circle29738b1b-2cff-4d8b-b3f6-58e38f2a4dc6",
      "type": "Circle",
      "stroke": "",
      "strokeWidth": 3,
      "x": 738.2107971829207,
      "y": 530.7699758788046,
      "radius": 50,
      "fill": "#000000",
      "ty": "Circle",
      "draggable": true,
      "rotation": 0,
      "scaleX": 1,
      "scaleY": 1,
      "offsetX": 0,
      "offsetY": 0,
      "skewX": 0,
      "skewY": 0
    }
  }
},
{
  "_id": 53,
  "templateId": "sixhat",
  "projectName": "모자",
  "thumbnail": "https://getidea-s3.s3.ap-northeast-2.amazonaws.com/thumbnailImage/sixhat.png",
  "lastUpdateTime": {
    "$date": "2024-02-15T11:46:47.733Z"
  },
  "data": {
    "Rect1": {},
    "null": {},
    "Arrow4": {
      "id": "Arrow4",
      "points": [
        null,
        null,
        null,
        null
      ],
      "pointerLength": 20,
      "stroke": "#000000",
      "rotation": null,
      "strokeWidth": 10,
      "fill": "#000000",
      "ty": "Line",
      "type": "Arrow",
      "lineJoin": "round",
      "x": null,
      "y": null,
      "draggable": true,
      "dashEnabled": true,
      "scaleX": null,
      "scaleY": null,
      "offsetX": 0,
      "offsetY": 0,
      "skewX": null,
      "skewY": 0
    },
    "Rect2": {
      "id": "Rect2",
      "type": "Rect",
      "stroke": "",
      "x": 99.68353249277288,
      "y": 151.2043189272229,
      "width": 100,
      "height": 100,
      "fill": "#000000",
      "ty": "Shape",
      "draggable": true,
      "rotation": 0,
      "scaleX": 1,
      "scaleY": 1,
      "offsetX": 0,
      "offsetY": 0,
      "skewX": 0,
      "skewY": 0
    }
  }
},
{
  "_id": 54,
  "templateId": "sixhat",
  "projectName": "20240215",
  "thumbnail": "https://getidea-s3.s3.ap-northeast-2.amazonaws.com/thumbnailImage/sixhat.png",
  "lastUpdateTime": {
    "$date": "2024-02-15T08:40:30.079Z"
  },
  "data": {
    "Circle7b606e21-48b7-450b-aa13-5e0d5596937b": {
      "id": "Circle7b606e21-48b7-450b-aa13-5e0d5596937b",
      "type": "Circle",
      "stroke": "",
      "strokeWidth": 3,
      "x": 909.2631900873968,
      "y": 323.8689675484251,
      "radius": 50,
      "fill": "#000000",
      "ty": "Circle",
      "draggable": true,
      "rotation": 0,
      "scaleX": 1,
      "scaleY": 1,
      "offsetX": 0,
      "offsetY": 0,
      "skewX": 0,
      "skewY": 0
    },
    "Rect574f51ad-9439-4b67-9eb6-d56892f635b4": {
      "id": "Rect574f51ad-9439-4b67-9eb6-d56892f635b4",
      "type": "Rect",
      "stroke": "",
      "strokeWidth": 3,
      "x": 500.1378760644105,
      "y": 275.89192213848196,
      "width": 100,
      "height": 100,
      "fill": "#000000",
      "ty": "Rect",
      "draggable": true,
      "rotation": 0,
      "scaleX": 1,
      "scaleY": 1,
      "offsetX": 0,
      "offsetY": 0,
      "skewX": 0,
      "skewY": 0
    },
    "Circlec9e5192e-e82a-44c3-9417-002ad85e92fd": {
      "id": "Circlec9e5192e-e82a-44c3-9417-002ad85e92fd",
      "type": "Circle",
      "stroke": "",
      "strokeWidth": 3,
      "x": 1142.334579249636,
      "y": 321.8699239896775,
      "radius": 50,
      "fill": "#000000",
      "ty": "Circle",
      "draggable": true,
      "rotation": 0,
      "scaleX": 1,
      "scaleY": 1,
      "offsetX": 0,
      "offsetY": 0,
      "skewX": 0,
      "skewY": 0
    }
  }
},
{
  "_id": 55,
  "templateId": "7check",
  "projectName": "7777",
  "thumbnail": "https://getidea-s3.s3.ap-northeast-2.amazonaws.com/thumbnailImage/7Check.png",
  "lastUpdateTime": {
    "$date": "2024-02-15T07:59:42.468Z"
  },
  "data": {
    "Rect736e1e61-4f09-4b65-b97a-210bf8097275": {
      "id": "Rect736e1e61-4f09-4b65-b97a-210bf8097275",
      "type": "Rect",
      "stroke": "",
      "strokeWidth": 3,
      "x": 182.04044364556037,
      "y": 401.8316663395826,
      "width": 100,
      "height": 100,
      "fill": "#000000",
      "ty": "Rect",
      "draggable": true,
      "rotation": 0,
      "scaleX": 1,
      "scaleY": 1,
      "offsetX": 0,
      "offsetY": 0,
      "skewX": 0,
      "skewY": 0
    },
    "Circle16d829b6-c62f-4ff5-ad1a-05ceff461331": {
      "id": "Circle16d829b6-c62f-4ff5-ad1a-05ceff461331",
      "type": "Circle",
      "stroke": "",
      "strokeWidth": 3,
      "x": 590.1654512772925,
      "y": 198.92874512669832,
      "radius": 50,
      "fill": "#000000",
      "ty": "Circle",
      "draggable": true,
      "rotation": 0,
      "scaleX": 1,
      "scaleY": 1,
      "offsetX": 0,
      "offsetY": 0,
      "skewX": 0,
      "skewY": 0
    }
  }
},
{
  "_id": 56,
  "templateId": "whiteboard",
  "projectName": "12345",
  "thumbnail": "https://getidea-s3.s3.ap-northeast-2.amazonaws.com/thumbnailImage/whiteboard.png",
  "lastUpdateTime": {
    "$date": "2024-02-15T11:44:19.020Z"
  },
  "data": {
    "Circle1": {
      "id": "Circle1",
      "type": "Circle",
      "stroke": "",
      "x": 520.0929772502473,
      "y": 381.98078814883394,
      "radius": 50,
      "fill": "#000000",
      "ty": "Shape",
      "draggable": true,
      "rotation": 0,
      "scaleX": 1,
      "scaleY": 1,
      "offsetX": 0,
      "offsetY": 0,
      "skewX": 0,
      "skewY": 0
    },
    "Rect1": {
      "id": "Rect1",
      "type": "Rect",
      "stroke": "",
      "x": 256.04075173095947,
      "y": 196.99149354782708,
      "width": 100,
      "height": 100,
      "fill": "#000000",
      "ty": "Shape",
      "draggable": true,
      "rotation": 0,
      "scaleX": 1,
      "scaleY": 1,
      "offsetX": 0,
      "offsetY": 0,
      "skewX": 0,
      "skewY": 0
    },
    "Circle2": {
      "id": "Circle2",
      "type": "Circle",
      "stroke": "",
      "x": 780,
      "y": 293.9858804467334,
      "radius": 50,
      "fill": "#000000",
      "ty": "Shape",
      "draggable": true,
      "rotation": 0,
      "scaleX": 1,
      "scaleY": 1,
      "offsetX": 0,
      "offsetY": 0,
      "skewX": 0,
      "skewY": 0
    },
    "Rect3": {
      "id": "Rect3",
      "type": "Rect",
      "stroke": "",
      "x": 216.03283877349156,
      "y": 462.9761009200856,
      "width": 100,
      "height": 100,
      "fill": "#000000",
      "ty": "Shape",
      "draggable": true,
      "rotation": 0,
      "scaleX": 1,
      "scaleY": 1,
      "offsetX": 0,
      "offsetY": 0,
      "skewX": 0,
      "skewY": 0
    },
    "Rect4": {
      "id": "Rect4",
      "type": "Rect",
      "stroke": "",
      "x": 773,
      "y": 439.9774318615821,
      "width": 100,
      "height": 100,
      "fill": "#000000",
      "ty": "Shape",
      "draggable": true,
      "rotation": 0,
      "scaleX": 1,
      "scaleY": 1,
      "offsetX": 0,
      "offsetY": 0,
      "skewX": 0,
      "skewY": 0
    },
    "RegularPolygon1": {
      "id": "RegularPolygon1",
      "type": "RegularPolygon",
      "stroke": "",
      "x": 315,
      "y": -11.99641224466177,
      "sides": 3,
      "radius": 50,
      "fill": "#000000",
      "ty": "Shape",
      "draggable": true,
      "rotation": 0,
      "scaleX": 1,
      "scaleY": 1,
      "offsetX": 0,
      "offsetY": 0,
      "skewX": 0,
      "skewY": 0
    },
    "RegularPolygon2": {
      "id": "RegularPolygon2",
      "type": "RegularPolygon",
      "stroke": "",
      "x": 665.1216617210682,
      "y": 179.99247728719402,
      "sides": 3,
      "radius": 50,
      "fill": "#000000",
      "ty": "Shape",
      "draggable": true,
      "rotation": 0,
      "scaleX": 1,
      "scaleY": 1,
      "offsetX": 0,
      "offsetY": 0,
      "skewX": 0,
      "skewY": 0
    },
    "Rect10": {
      "id": "Rect10",
      "type": "Rect",
      "stroke": "",
      "x": 548,
      "y": 305.98518604247437,
      "width": 100,
      "height": 100,
      "fill": "#000000",
      "ty": "Shape",
      "draggable": true,
      "rotation": 0,
      "scaleX": 1,
      "scaleY": 1,
      "offsetX": 0,
      "offsetY": 0,
      "skewX": 0,
      "skewY": 0
    },
    "Rect9": {
      "id": "Rect9",
      "type": "Rect",
      "stroke": "",
      "x": 628,
      "y": 162.99346102656096,
      "width": 100,
      "height": 100,
      "fill": "#000000",
      "ty": "Shape",
      "draggable": true,
      "rotation": 0,
      "scaleX": 1,
      "scaleY": 1,
      "offsetX": 0,
      "offsetY": 0,
      "skewX": 0,
      "skewY": 0
    },
    "Rect8": {
      "id": "Rect8",
      "type": "Rect",
      "stroke": "",
      "x": 377,
      "y": 479.97511718071866,
      "width": 100,
      "height": 100,
      "fill": "#000000",
      "ty": "Shape",
      "draggable": true,
      "rotation": 0,
      "scaleX": 1,
      "scaleY": 1,
      "offsetX": 0,
      "offsetY": 0,
      "skewX": 0,
      "skewY": 0
    },
    "Rect7": {
      "id": "Rect7",
      "type": "Rect",
      "stroke": "",
      "x": 172,
      "y": 323.9841444360859,
      "width": 100,
      "height": 100,
      "fill": "#000000",
      "ty": "Shape",
      "draggable": true,
      "rotation": 0,
      "scaleX": 1,
      "scaleY": 1,
      "offsetX": 0,
      "offsetY": 0,
      "skewX": 0,
      "skewY": 0
    },
    "Rect6": {
      "id": "Rect6",
      "type": "Rect",
      "stroke": "",
      "x": 328,
      "y": 61.99930559574098,
      "width": 100,
      "height": 100,
      "fill": "#000000",
      "ty": "Shape",
      "draggable": true,
      "rotation": 0,
      "scaleX": 1,
      "scaleY": 1,
      "offsetX": 0,
      "offsetY": 0,
      "skewX": 0,
      "skewY": 0
    },
    "Rect5": {
      "id": "Rect5",
      "type": "Rect",
      "stroke": "",
      "x": 526,
      "y": 531.9721080955962,
      "width": 100,
      "height": 100,
      "fill": "#000000",
      "ty": "Shape",
      "draggable": true,
      "rotation": 0,
      "scaleX": 1,
      "scaleY": 1,
      "offsetX": 0,
      "offsetY": 0,
      "skewX": 0,
      "skewY": 0
    },
    "Rect2": {
      "id": "Rect2",
      "type": "Rect",
      "stroke": "",
      "x": 838,
      "y": 113.9962965106186,
      "width": 100,
      "height": 100,
      "fill": "#000000",
      "ty": "Shape",
      "draggable": true,
      "rotation": 0,
      "scaleX": 1,
      "scaleY": 1,
      "offsetX": 0,
      "offsetY": 0,
      "skewX": 0,
      "skewY": 0
    }
  }
},
{
  "_id": 57,
  "templateId": "whiteboard",
  "projectName": "채팅 테스트",
  "thumbnail": "https://getidea-s3.s3.ap-northeast-2.amazonaws.com/thumbnailImage/whiteboard.png",
  "lastUpdateTime": {
    "$date": "2024-02-15T08:36:44.169Z"
  },
  "data": {}
},
{
  "_id": 58,
  "templateId": "bubbleChat",
  "projectName": "dd",
  "thumbnail": "https://getidea-s3.s3.ap-northeast-2.amazonaws.com/thumbnailImage/bubbleChat.png",
  "lastUpdateTime": {
    "$date": "2024-02-15T08:36:59.693Z"
  },
  "data": {}
},
{
  "_id": 59,
  "templateId": "bubbleChat",
  "projectName": "ㅑㅑ",
  "thumbnail": "https://getidea-s3.s3.ap-northeast-2.amazonaws.com/thumbnailImage/bubbleChat.png",
  "lastUpdateTime": {
    "$date": "2024-02-15T11:43:18.012Z"
  },
  "data": {
    "Circle1": {
      "id": "Circle1",
      "type": "Circle",
      "stroke": "",
      "x": 619.4277163224968,
      "y": 279.4190554740553,
      "radius": 119.27452069537392,
      "fill": "#000000",
      "ty": "Shape",
      "draggable": true,
      "rotation": 0,
      "scaleX": 1,
      "scaleY": 1,
      "offsetX": 0,
      "offsetY": 0,
      "skewX": 0,
      "skewY": 0,
      "width": 238.54904139074802,
      "height": 238.54904139074785
    },
    "Rect1": {
      "id": "Rect1",
      "type": "Rect",
      "stroke": "",
      "x": 596.167289624818,
      "y": 190.12646793134599,
      "width": 100,
      "height": 100,
      "fill": "#000000",
      "ty": "Shape",
      "draggable": true,
      "rotation": 0,
      "scaleX": 1,
      "scaleY": 1,
      "offsetX": 0,
      "offsetY": 0,
      "skewX": 0,
      "skewY": 0
    }
  }
},
{
  "_id": 60,
  "templateId": "whiteboard",
  "projectName": "프로젝트",
  "thumbnail": "https://getidea-s3.s3.ap-northeast-2.amazonaws.com/thumbnailImage/whiteboard.png",
  "lastUpdateTime": {
    "$date": "2024-02-15T11:27:05.163Z"
  },
  "data": {
    "Rect1": {
      "id": "Rect1",
      "type": "Rect",
      "stroke": "#ffffff",
      "x": 453.1234756754607,
      "y": 29.984938089993307,
      "width": 435.9731694179361,
      "height": 435.9731694179362,
      "fill": "#000000",
      "ty": "Shape",
      "draggable": true,
      "rotation": 0,
      "scaleX": 1,
      "scaleY": 1,
      "skewX": 0,
      "skewY": 0,
      "offsetX": 0,
      "offsetY": 0
    },
    "Circle3": {
      "id": "Circle3",
      "type": "Circle",
      "stroke": "",
      "x": 762.2181505730226,
      "y": 251.1513721955671,
      "radius": 50,
      "fill": "#e000a5",
      "ty": "Shape",
      "draggable": true,
      "rotation": 0,
      "scaleX": 1,
      "scaleY": 1,
      "offsetX": 0,
      "offsetY": 0,
      "skewX": 0,
      "skewY": 0
    },
    "Circle2": {
      "id": "Circle2",
      "type": "Circle",
      "stroke": "",
      "x": 678.192413707666,
      "y": 320.2033357850901,
      "radius": 50,
      "fill": "#000000",
      "ty": "Shape",
      "draggable": true,
      "rotation": 0,
      "scaleX": 1,
      "scaleY": 1,
      "offsetX": 0,
      "offsetY": 0,
      "skewX": 0,
      "skewY": 0
    },
    "Arrow3": {
      "id": "Arrow3",
      "points": [
        null,
        null,
        null,
        null
      ],
      "pointerLength": 20,
      "stroke": "#e000a5",
      "rotation": 0,
      "strokeWidth": 10,
      "fill": "#e000a5",
      "ty": "Line",
      "type": "Arrow",
      "lineJoin": "round",
      "x": 198.06066546834057,
      "y": 73.05497597152434,
      "draggable": true,
      "dashEnabled": true,
      "scaleX": 1,
      "scaleY": 1,
      "offsetX": 0,
      "offsetY": 0,
      "skewX": 0,
      "skewY": 0
    },
    "Arrow2": {
      "id": "Arrow2",
      "points": [
        null,
        null,
        null,
        null
      ],
      "pointerLength": 20,
      "stroke": "#e000a5",
      "rotation": 0,
      "strokeWidth": 10,
      "fill": "#e000a5",
      "ty": "Line",
      "type": "Arrow",
      "lineJoin": "round",
      "x": 227.0695508147137,
      "y": 95.07154407253168,
      "draggable": true,
      "dashEnabled": true,
      "scaleX": 1,
      "scaleY": 1,
      "offsetX": 0,
      "offsetY": 0,
      "skewX": 0,
      "skewY": 0
    },
    "Arrow1": {
      "id": "Arrow1",
      "points": [
        null,
        null,
        null,
        null
      ],
      "pointerLength": 20,
      "stroke": "#e000a5",
      "rotation": 0,
      "strokeWidth": 10,
      "fill": "#e000a5",
      "ty": "Line",
      "type": "Arrow",
      "lineJoin": "round",
      "x": 277.08487037742594,
      "y": 151.11371742055036,
      "draggable": true,
      "dashEnabled": true,
      "scaleX": 1,
      "scaleY": 1,
      "offsetX": 0,
      "offsetY": 0,
      "skewX": 0,
      "skewY": 0
    },
    "Text-1": {
      "id": "Text-1",
      "text": "텍스트입니다",
      "x": 520.1593234522076,
      "y": 411.3095222506371,
      "ty": "Text",
      "draggable": true,
      "style": {
        "zIndex": 100
      },
      "fill": "black",
      "rotation": 0,
      "scaleX": 1,
      "scaleY": 1,
      "offsetX": 0,
      "offsetY": 0,
      "skewX": 0,
      "skewY": 0
    }
  }
},
{
  "_id": 61,
  "templateId": "bubbleChat",
  "projectName": "우와",
  "thumbnail": "https://getidea-s3.s3.ap-northeast-2.amazonaws.com/thumbnailImage/bubbleChat.png",
  "lastUpdateTime": {
    "$date": "2024-02-15T11:27:26.974Z"
  },
  "data": {}
},
{
  "_id": 62,
  "templateId": "bubbleChat",
  "projectName": "test",
  "thumbnail": "https://getidea-s3.s3.ap-northeast-2.amazonaws.com/thumbnailImage/bubbleChat.png",
  "lastUpdateTime": {
    "$date": "2024-02-15T11:31:48.190Z"
  },
  "data": {}
},
{
  "_id": 63,
  "templateId": "bubbleChat",
  "projectName": "초대테스트",
  "thumbnail": "https://getidea-s3.s3.ap-northeast-2.amazonaws.com/thumbnailImage/bubbleChat.png",
  "lastUpdateTime": {
    "$date": "2024-02-15T11:51:31.519Z"
  },
  "data": {}
},
{
  "_id": 64,
  "templateId": "sixhat",
  "projectName": "6",
  "thumbnail": "https://getidea-s3.s3.ap-northeast-2.amazonaws.com/thumbnailImage/sixhat.png",
  "lastUpdateTime": {
    "$date": "2024-02-15T11:52:43.596Z"
  },
  "data": {}
},
{
  "_id": 65,
  "templateId": "sixhat",
  "projectName": "new pjt",
  "thumbnail": "https://getidea-s3.s3.ap-northeast-2.amazonaws.com/thumbnailImage/sixhat.png",
  "lastUpdateTime": {
    "$date": "2024-02-15T12:38:23.272Z"
  },
  "data": {
    "Rect1": {
      "id": "Rect1",
      "type": "Rect",
      "stroke": "",
      "x": 498.180517152742,
      "y": 323.98414443608584,
      "width": 100,
      "height": 100,
      "fill": "#000000",
      "ty": "Shape",
      "draggable": true,
      "rotation": 0,
      "scaleX": 1,
      "scaleY": 1,
      "offsetX": 0,
      "offsetY": 0,
      "skewX": 0,
      "skewY": 0
    },
    "Circle2": {
      "id": "Circle2",
      "type": "Circle",
      "stroke": "",
      "x": 278.09187033666336,
      "y": 380.98084601585555,
      "radius": 50,
      "fill": "#000000",
      "ty": "Shape",
      "draggable": true,
      "rotation": 0,
      "scaleX": 1,
      "scaleY": 1,
      "offsetX": 0,
      "offsetY": 0,
      "skewX": 0,
      "skewY": 0
    }
  }
},
{
  "_id": 66,
  "templateId": "bubbleChat",
  "projectName": "kkk",
  "thumbnail": "https://getidea-s3.s3.ap-northeast-2.amazonaws.com/thumbnailImage/bubbleChat.png",
  "lastUpdateTime": {
    "$date": "2024-02-15T12:07:38.132Z"
  },
  "data": {}
},
{
  "_id": 67,
  "templateId": "bubbleChat",
  "projectName": "ddi",
  "thumbnail": "https://getidea-s3.s3.ap-northeast-2.amazonaws.com/thumbnailImage/bubbleChat.png",
  "lastUpdateTime": {
    "$date": "2024-02-15T12:08:26.689Z"
  },
  "data": {}
},
{
  "_id": 68,
  "templateId": "whiteboard",
  "projectName": "1",
  "thumbnail": "https://getidea-s3.s3.ap-northeast-2.amazonaws.com/thumbnailImage/whiteboard.png",
  "lastUpdateTime": {
    "$date": "2024-02-15T12:38:02.932Z"
  },
  "data": {
    "Rect1": {
      "id": "Rect1",
      "type": "Rect",
      "stroke": "",
      "x": 430.1531172277722,
      "y": 423.97835773392734,
      "width": 100,
      "height": 100,
      "fill": "#000000",
      "ty": "Shape",
      "draggable": true,
      "rotation": 0,
      "scaleX": 1,
      "scaleY": 1,
      "offsetX": 0,
      "offsetY": 0,
      "skewX": 0,
      "skewY": 0
    },
    "Circle2": {
      "id": "Circle2",
      "type": "Circle",
      "stroke": "",
      "x": 274.090258576371,
      "y": 218.99022047335222,
      "radius": 50,
      "fill": "#000000",
      "ty": "Shape",
      "draggable": true,
      "rotation": 0,
      "scaleX": 1,
      "scaleY": 1,
      "offsetX": 0,
      "offsetY": 0,
      "skewX": 0,
      "skewY": 0
    },
    "RegularPolygon3": {
      "id": "RegularPolygon3",
      "type": "RegularPolygon",
      "stroke": "",
      "x": 442.15795250864926,
      "y": 622.9668421966319,
      "sides": 3,
      "radius": 50,
      "fill": "#000000",
      "ty": "Shape",
      "draggable": true,
      "rotation": 0,
      "scaleX": 1,
      "scaleY": 1,
      "offsetX": 0,
      "offsetY": 0,
      "skewX": 0,
      "skewY": 0
    },
    "Circle4": {
      "id": "Circle4",
      "type": "Circle",
      "stroke": "",
      "x": 738.2772227702824,
      "y": 264.9875585903593,
      "radius": 50,
      "fill": "#000000",
      "ty": "Shape",
      "draggable": true,
      "rotation": 0,
      "scaleX": 1,
      "scaleY": 1,
      "offsetX": 0,
      "offsetY": 0,
      "skewX": 0,
      "skewY": 0
    },
    "Circle5": {
      "id": "Circle5",
      "type": "Circle",
      "stroke": "",
      "x": 228.07172333300912,
      "y": 450.9767953243446,
      "radius": 50,
      "fill": "#000000",
      "ty": "Shape",
      "draggable": true,
      "rotation": 0,
      "scaleX": 1,
      "scaleY": 1,
      "offsetX": 0,
      "offsetY": 0,
      "skewX": 0,
      "skewY": 0
    },
    "RegularPolygon6": {
      "id": "RegularPolygon6",
      "type": "RegularPolygon",
      "stroke": "",
      "x": 148.03948812716234,
      "y": 306.9851281754528,
      "sides": 3,
      "radius": 50,
      "fill": "#000000",
      "ty": "Shape",
      "draggable": true,
      "rotation": 0,
      "scaleX": 1,
      "scaleY": 1,
      "offsetX": 0,
      "offsetY": 0,
      "skewX": 0,
      "skewY": 0
    },
    "Rect7": {
      "id": "Rect7",
      "type": "Rect",
      "stroke": "",
      "x": 94.01772936321572,
      "y": 400.97968867542386,
      "width": 100,
      "height": 100,
      "fill": "#000000",
      "ty": "Shape",
      "draggable": true,
      "rotation": 0,
      "scaleX": 1,
      "scaleY": 1,
      "offsetX": 0,
      "offsetY": 0,
      "skewX": 0,
      "skewY": 0
    },
    "Rect8": {
      "id": "Rect8",
      "type": "Rect",
      "stroke": "",
      "x": 775.2921315529866,
      "y": 293.9858804467334,
      "width": 100,
      "height": 100,
      "fill": "#000000",
      "ty": "Shape",
      "draggable": true,
      "rotation": 0,
      "scaleX": 1,
      "scaleY": 1,
      "offsetX": 0,
      "offsetY": 0,
      "skewX": 0,
      "skewY": 0
    },
    "Circle9": {
      "id": "Circle9",
      "type": "Circle",
      "stroke": "",
      "x": 948.3618401856303,
      "y": 591.9686360743012,
      "radius": 50,
      "fill": "#000000",
      "ty": "Shape",
      "draggable": true,
      "rotation": 0,
      "scaleX": 1,
      "scaleY": 1,
      "offsetX": 0,
      "offsetY": 0,
      "skewX": 0,
      "skewY": 0
    },
    "RegularPolygon10": {
      "id": "RegularPolygon10",
      "type": "RegularPolygon",
      "stroke": "",
      "x": 319.10839087965985,
      "y": 582.9691568774956,
      "sides": 3,
      "radius": 50,
      "fill": "#000000",
      "ty": "Shape",
      "draggable": true,
      "rotation": 0,
      "scaleX": 1,
      "scaleY": 1,
      "offsetX": 0,
      "offsetY": 0,
      "skewX": 0,
      "skewY": 0
    },
    "Rect11": {
      "id": "Rect11",
      "type": "Rect",
      "stroke": "",
      "x": 382.1337761042641,
      "y": 128.99542850529485,
      "width": 100,
      "height": 100,
      "fill": "#000000",
      "ty": "Shape",
      "draggable": true,
      "rotation": 0,
      "scaleX": 1,
      "scaleY": 1,
      "offsetX": 0,
      "offsetY": 0,
      "skewX": 0,
      "skewY": 0
    },
    "Circle12": {
      "id": "Circle12",
      "type": "Circle",
      "stroke": "",
      "x": 396.1394172652874,
      "y": 302.98535964353914,
      "radius": 50,
      "fill": "#000000",
      "ty": "Shape",
      "draggable": true,
      "rotation": 0,
      "scaleX": 1,
      "scaleY": 1,
      "offsetX": 0,
      "offsetY": 0,
      "skewX": 0,
      "skewY": 0
    },
    "RegularPolygon13": {
      "id": "RegularPolygon13",
      "type": "RegularPolygon",
      "stroke": "",
      "x": 711.2663433883091,
      "y": 681.9634280423587,
      "sides": 3,
      "radius": 50,
      "fill": "#000000",
      "ty": "Shape",
      "draggable": true,
      "rotation": 0,
      "scaleX": 1,
      "scaleY": 1,
      "offsetX": 0,
      "offsetY": 0,
      "skewX": 0,
      "skewY": 0
    },
    "Circle14": {
      "id": "Circle14",
      "type": "Circle",
      "stroke": "",
      "x": 546.1998582762501,
      "y": 199.9913199467623,
      "radius": 50,
      "fill": "#000000",
      "ty": "Shape",
      "draggable": true,
      "rotation": 0,
      "scaleX": 1,
      "scaleY": 1,
      "offsetX": 0,
      "offsetY": 0,
      "skewX": 0,
      "skewY": 0
    }
  }
},
{
  "_id": 69,
  "templateId": "bubbleChat",
  "projectName": "ooooo",
  "thumbnail": "https://getidea-s3.s3.ap-northeast-2.amazonaws.com/thumbnailImage/bubbleChat.png",
  "lastUpdateTime": {
    "$date": "2024-02-15T12:55:26.847Z"
  },
  "data": {}
}]